poel/__init__.py
poel/api/__init__.py
poel/api/easydoc.py
poel/core/__init__.py
poel/core/parse.py
poel/lib/__init__.py
poel/lib/config.py
poel-0.0.3.dist-info/LICENSE
poel-0.0.3.dist-info/METADATA
poel-0.0.3.dist-info/WHEEL
poel-0.0.3.dist-info/top_level.txt
poel-0.0.3.dist-info/RECORD
