Metadata-Version: 2.1
Name: poel
Version: 0.0.3
Summary: pip install poel
Home-page: https://www.python-office.com/
Author: CoderWanFeng
Author-email: 1957875073@qq.com
License: MIT
Project-URL: Bug Tracker, https://github.com/CoderWanFeng/poel/issues
Project-URL: Documentation, https://github.com/CoderWanFeng/poel/blob/main/README.md
Project-URL: Source Code, https://github.com/CoderWanFeng/poel
Platform: any
Requires-Python: >=3.7
License-File: LICENSE
Requires-Dist: loguru
Requires-Dist: pofile
Requires-Dist: requests
